{
  "4": {
    "Colère": 0,
    "Dégoût": 1,
    "Joie": 0,
    "Peur": 0,
    "Surprise": 0,
    "Tristesse": 0,
    "Admiration": 0,
    "Culpabilité": 0,
    "Embarras": 0,
    "Fierté": 0,
    "Jalousie": 0,
    "notes": "",
    "reviewed_at": "2026-03-12T11:53:23.187052+00:00"
  },
  "5": {
    "Colère": 0,
    "Dégoût": 1,
    "Joie": 0,
    "Peur": 0,
    "Surprise": 0,
    "Tristesse": 0,
    "Admiration": 0,
    "Culpabilité": 0,
    "Embarras": 0,
    "Fierté": 0,
    "Jalousie": 0,
    "notes": "",
    "reviewed_at": "2026-03-12T10:29:30.360375+00:00"
  },
  "8": {
    "Colère": 0,
    "Dégoût": 0,
    "Joie": 0,
    "Peur": 0,
    "Surprise": 0,
    "Tristesse": 0,
    "Admiration": 0,
    "Culpabilité": 0,
    "Embarras": 0,
    "Fierté": 0,
    "Jalousie": 0,
    "notes": "",
    "reviewed_at": "2026-03-12T10:29:44.411529+00:00"
  },
  "9": {
    "Colère": 0,
    "Dégoût": 0,
    "Joie": 0,
    "Peur": 0,
    "Surprise": 0,
    "Tristesse": 0,
    "Admiration": 0,
    "Culpabilité": 0,
    "Embarras": 0,
    "Fierté": 0,
    "Jalousie": 0,
    "notes": "",
    "reviewed_at": "2026-03-12T10:29:53.953429+00:00"
  },
  "14": {
    "Colère": 0,
    "Dégoût": 1,
    "Joie": 0,
    "Peur": 0,
    "Surprise": 0,
    "Tristesse": 0,
    "Admiration": 0,
    "Culpabilité": 0,
    "Embarras": 0,
    "Fierté": 0,
    "Jalousie": 0,
    "notes": "",
    "reviewed_at": "2026-03-12T10:30:18.702209+00:00"
  },
  "22": {
    "Colère": 1,
    "Dégoût": 0,
    "Joie": 0,
    "Peur": 0,
    "Surprise": 0,
    "Tristesse": 0,
    "Admiration": 0,
    "Culpabilité": 0,
    "Embarras": 1,
    "Fierté": 0,
    "Jalousie": 0,
    "notes": "",
    "reviewed_at": "2026-03-12T10:30:42.056952+00:00"
  },
  "23": {
    "Colère": 0,
    "Dégoût": 0,
    "Joie": 0,
    "Peur": 0,
    "Surprise": 0,
    "Tristesse": 0,
    "Admiration": 0,
    "Culpabilité": 0,
    "Embarras": 0,
    "Fierté": 0,
    "Jalousie": 0,
    "notes": "",
    "reviewed_at": "2026-03-12T10:30:48.295012+00:00"
  },
  "26": {
    "Colère": 1,
    "Dégoût": 1,
    "Joie": 0,
    "Peur": 0,
    "Surprise": 0,
    "Tristesse": 0,
    "Admiration": 0,
    "Culpabilité": 0,
    "Embarras": 0,
    "Fierté": 0,
    "Jalousie": 0,
    "notes": "",
    "reviewed_at": "2026-03-12T10:30:51.340036+00:00"
  },
  "28": {
    "Colère": 0,
    "Dégoût": 0,
    "Joie": 0,
    "Peur": 0,
    "Surprise": 0,
    "Tristesse": 0,
    "Admiration": 0,
    "Culpabilité": 0,
    "Embarras": 0,
    "Fierté": 0,
    "Jalousie": 0,
    "notes": "",
    "reviewed_at": "2026-03-12T10:30:59.901447+00:00"
  },
  "34": {
    "Colère": 1,
    "Dégoût": 1,
    "Joie": 0,
    "Peur": 0,
    "Surprise": 0,
    "Tristesse": 0,
    "Admiration": 0,
    "Culpabilité": 0,
    "Embarras": 0,
    "Fierté": 0,
    "Jalousie": 0,
    "notes": "",
    "reviewed_at": "2026-03-12T10:31:03.223239+00:00"
  },
  "49": {
    "Colère": 0,
    "Dégoût": 0,
    "Joie": 0,
    "Peur": 0,
    "Surprise": 0,
    "Tristesse": 0,
    "Admiration": 0,
    "Culpabilité": 0,
    "Embarras": 0,
    "Fierté": 0,
    "Jalousie": 0,
    "notes": "",
    "reviewed_at": "2026-03-12T10:31:06.693223+00:00"
  },
  "64": {
    "Colère": 0,
    "Dégoût": 1,
    "Joie": 0,
    "Peur": 0,
    "Surprise": 0,
    "Tristesse": 0,
    "Admiration": 0,
    "Culpabilité": 0,
    "Embarras": 0,
    "Fierté": 0,
    "Jalousie": 0,
    "notes": "",
    "reviewed_at": "2026-03-12T10:31:14.057287+00:00"
  },
  "66": {
    "Colère": 1,
    "Dégoût": 1,
    "Joie": 0,
    "Peur": 0,
    "Surprise": 0,
    "Tristesse": 0,
    "Admiration": 0,
    "Culpabilité": 0,
    "Embarras": 0,
    "Fierté": 0,
    "Jalousie": 0,
    "notes": "",
    "reviewed_at": "2026-03-12T10:31:19.148709+00:00"
  },
  "71": {
    "Colère": 0,
    "Dégoût": 0,
    "Joie": 0,
    "Peur": 0,
    "Surprise": 0,
    "Tristesse": 0,
    "Admiration": 0,
    "Culpabilité": 0,
    "Embarras": 0,
    "Fierté": 0,
    "Jalousie": 0,
    "notes": "",
    "reviewed_at": "2026-03-12T10:31:23.380991+00:00"
  },
  "81": {
    "Colère": 0,
    "Dégoût": 1,
    "Joie": 1,
    "Peur": 0,
    "Surprise": 0,
    "Tristesse": 0,
    "Admiration": 0,
    "Culpabilité": 0,
    "Embarras": 0,
    "Fierté": 0,
    "Jalousie": 0,
    "notes": "",
    "reviewed_at": "2026-03-12T10:31:28.092846+00:00"
  },
  "100": {
    "Colère": 0,
    "Dégoût": 0,
    "Joie": 1,
    "Peur": 0,
    "Surprise": 0,
    "Tristesse": 0,
    "Admiration": 0,
    "Culpabilité": 0,
    "Embarras": 0,
    "Fierté": 1,
    "Jalousie": 0,
    "notes": "",
    "reviewed_at": "2026-03-12T10:31:28.840775+00:00"
  },
  "102": {
    "Colère": 1,
    "Dégoût": 1,
    "Joie": 0,
    "Peur": 0,
    "Surprise": 0,
    "Tristesse": 0,
    "Admiration": 0,
    "Culpabilité": 0,
    "Embarras": 0,
    "Fierté": 0,
    "Jalousie": 0,
    "notes": "",
    "reviewed_at": "2026-03-12T10:31:31.864723+00:00"
  }
}